pcmap/__init__.py
pcmap/__main__.py
pcmap/ctype.py
pcmap/deserializer.py
pcmap/generators.py
pcmap/io.py
pcmap/plugins.py
pcmap/sasa/LSB_atom_map.py
pcmap/sasa/__init__.py
pcmap/sasa/atom_map.py
pcmap/sasa/cg_vdw_map_utils.py
pcmap/sasa/dto.py
pcmap/sasa/generators/mda_frames.py
pcmap/sasa/generators/pdb_lists.py
pcmap/sasa/run_many.py
pcmap/threads.py
pcmap/utils.py
pcmap-1.1.4.dist-info/LICENSE
pcmap-1.1.4.dist-info/WHEEL
pcmap-1.1.4.dist-info/METADATA
pcmap-1.1.4.dist-info/RECORD
