Metadata-Version: 2.1
Name: pcmap
Version: 1.1.4
Summary: Computing contact map for protein structures
Home-page: https://github.com/MMSB-MOBI/pcmap
License: GPL
Keywords: protein,structure,atomic contact,SASA
Author: Guillaume Launay
Author-email: guillaume.launay@ibcp.fr
Requires-Python: >=3.9,<3.11
Classifier: Development Status :: 5 - Production/Stable
Classifier: Intended Audience :: Science/Research
Classifier: License :: OSI Approved :: MIT License
Classifier: License :: Other/Proprietary License
Classifier: Programming Language :: Python :: 3
Classifier: Programming Language :: Python :: 3.10
Classifier: Programming Language :: Python :: 3.9
Classifier: Topic :: Scientific/Engineering :: Bio-Informatics
Classifier: Topic :: Software Development :: Libraries :: Python Modules
Requires-Dist: MDAnalysis (>=2.3.0,<3.0.0)
Requires-Dist: ccmap (>=4.0.2,<5.0.0)
Requires-Dist: docopt (>=0.6.2,<0.7.0)
Requires-Dist: ipykernel (>=6.20.0,<7.0.0)
Requires-Dist: numpy (>=1.19.0,<2.0.0)
Requires-Dist: pypstruct (>=0.1.2,<0.2.0)
Requires-Dist: tqdm (>=4.64.1,<5.0.0)
